setup.py
mdma/__init__.py
mdma.egg-info/PKG-INFO
mdma.egg-info/SOURCES.txt
mdma.egg-info/dependency_links.txt
mdma.egg-info/requires.txt
mdma.egg-info/top_level.txt