Metadata-Version: 1.0
Name: mdma
Version: 0.1.2
Summary: ipython notebook markdown magic
Home-page: UNKNOWN
Author: Erik Gafni
Author-email: egafni@gmail.com
License: GPLv2
Platform: UNKNOWN
